{
    "journal": {
      "nomJournal": "HallyuPulse",
      "phraseAccroche": "Catch the waves of K-pop and ride the pulse of its magic.",
      "texteAppelAction": "Rejoignez notre newsletter pour suivre vos idols préférés",
      "button-nav":"Follow",
      "bouton-article": "Read the article",
      "articlePrincipal": {
        "titre": "BTS en tête des charts mondiaux avec leur nouvel album",
        "description": "Le groupe légendaire revient avec un album qui bat tous les records.",
        "date": "1er Décembre 2024",
        "theme": "Actualités",
        "image": "https://essentialhomme.fr/wp-content/uploads/2023/03/BTS-The-Phenomenon-of-Brand-Collaborations.webp",
        "link": "https://altselection.com/les-membres-de-bts-sortiront-plusieurs-albums-en-2024-malgre-leur-enrolement/"
      },
      "navigation": [
        { "nom": "Actualités", "lien": "#actualites" },
        { "nom": "Concerts", "lien": "#concerts" },
        { "nom": "Groupes", "lien": "#groupes" },
        { "nom": "Nouveaux talents", "lien": "#nouveauxtalents" },
        { "nom": "Mode & Style", "lien": "#modestyle" },
        { "nom": "Collaborations", "lien": "#collaborations" }
      ],
      "articles": [
        {
          "titre": "BLACKPINK annonce une tournée mondiale inédite",
          "date": "28 Novembre 2024",
          "theme": "Concerts",
          "image": "images/BlackPink.jpg",
          "link": "https://www.vogue.fr/article/blackpink-retour-album-tournee-2025"
        },
        {
          "titre": "NCT : Tout ce qu'il faut savoir sur leurs multiples sous-unités",
          "date": "20 Novembre 2024",
          "theme": "Groupes",
          "image": "https://upload.wikimedia.org/wikipedia/commons/thumb/e/ee/NCT_Dream_at_the_MMA_2023_Awards.jpg/1100px-NCT_Dream_at_the_MMA_2023_Awards.jpg",
          "link": "https://www.soompi.com/article/1612084wpp/nct-universe-lastart-announces-final-7-members-who-will-debut-in-nct"
        },
        {
          "titre": "Les rookies à suivre en 2025 : NewJeans, ZEROBASEONE et plus",
          "date": "15 Novembre 2024",
          "theme": "Nouveaux talents",
          "image": "images/rookies.jpeg",
          "link": "https://k-gen.fr/top-30-par-reputation-des-groupes-rookies-de-k-pop-de-decembre-2024/"
        },
        {
          "titre": "Les collaborations K-pop x mode qui font sensation",
          "date": "10 Novembre 2024",
          "theme": "Mode & Style",
          "image": "https://miro.medium.com/v2/resize:fit:2000/1*04zqcibyATDgrFdzdUk9GA.jpeg",
          "link": "https://www.kpops-lifestyle.com/crush-mode-les-collaborations-incontournables-entre-marques-et-idols-k-pop"
        },
        {
          "titre": "Stray Kids : Un succès fulgurant dans l'industrie mondiale",
          "date": "5 Novembre 2024",
          "theme": "Groupes",
          "image": "https://cdn.ticketle.net/images/artists/stray-kids_c77c755bed4d.jpg?class=hr800",
          "link": "https://blog.ticketmaster.fr/musique/stray-kids-stade-de-france-2025/"
        }
      ],
      "themes": [
        {
          "nom": "Actualités",
          "description": "Les dernières nouvelles et annonces dans le monde de la K-pop."
        },
        {
          "nom": "Concerts",
          "description": "Toutes les informations sur les tournées et performances live."
        },
        {
          "nom": "Groupes",
          "description": "Focus sur les groupes emblématiques et en pleine ascension."
        },
        {
          "nom": "Nouveaux talents",
          "description": "Les rookies et nouveaux artistes qui redéfinissent la scène K-pop."
        },
        {
          "nom": "Mode & Style",
          "description": "Les tendances mode dictées par vos idols préférés."
        },
        {
          "nom": "Collaborations",
          "description": "Les partenariats entre stars de la K-pop et autres industries."
        }
      ],
      "auteurs": [
        {
          "prenom": "Moana",
          "typeExperience": "Correspondante K-pop",
          "presentation": "Basée à Séoul, <br>je couvre les actualités des idols et des agences  de divertissement.",
          "linkedin": "https://www.linkedin.com/in/moana-d",
          "github": "https://github.com/TheMoana",
          "image": "images/avatarMoana.png"
        },
        {
          "prenom": "Oumou",
          "typeExperience": "Chroniqueuse mode K-pop",
          "presentation": "Passionnée par le style des idols, j'analyse leurs looks iconiques et les collaborations de mode.",
          "linkedin": "www.linkedin.com/in/oumou-bathily",
          "github": "https://github.com/Oumou-stack",
          "image": "images/avatarOumouTransparent.png"
        },
        {
          "prenom": "Marie",
          "typeExperience": "Expert fanbase",
          "presentation": "Ancien administrateur de fanclubs, je partage des anecdotes et des analyses sur la dynamique des fandoms.",
          "linkedin": "https://www.linkedin.com/in/marie-france-lunganga/",
          "github": "https://github.com/mariefrancelng",
          "image": "images/avatarMarie.jpeg"
        }
      ]
    }
  }
  